bc/__init__.py
bc/_version.py
bc/dev/__init__.py
bc/dev/decorators.py
bc/dev/handlers.py
bc/dev/utils.py
bc/dev/wrappers.py
bordercontrol-0.2.0.0.5.dist-info/LICENSE.txt
bordercontrol-0.2.0.0.5.dist-info/METADATA
bordercontrol-0.2.0.0.5.dist-info/WHEEL
bordercontrol-0.2.0.0.5.dist-info/top_level.txt
bordercontrol-0.2.0.0.5.dist-info/RECORD
