Metadata-Version: 2.1
Name: bordercontrol
Version: 0.2.0.0.5
Summary: NATS wrapper for fast scanner development
Home-page: UNKNOWN
Author: Gleb Lysov
Author-email: lysov.g.v@gmail.com
License: UNKNOWN
Platform: UNKNOWN
Classifier: Development Status :: 3 - Alpha
Classifier: Programming Language :: Python :: 3.5
Requires-Dist: asyncio-nats-client
Requires-Dist: python-dateutil
